{
    "openapi": "3.0.0",
    "info": {
        "title": "ws-terms-tools",
        "description": "",
        "version": "2.1.0",
        "termsOfService": "https://services.istex.fr/",
        "contact": {
            "name": "Inist-CNRS",
            "url": "https://www.inist.fr/nous-contacter/"
        }
    },
    "servers": [
        {
            "x-comment": "Will be automatically completed by the ezs server."
        },
        {
            "url": "http://vptermsuite.intra.inist.fr:49175/",
            "description": "Latest version for production",
            "x-profil": "Standard"
        }
    ],
    "tags": [
        {
            "name": "NLP",
            "description": "Boite à outils de POS tagging et d'annotation de termes",
            "externalDocs": {
                "description": "Plus de documentation",
                "url": "https://github.com/inist-cnrs/web-services/tree/main/services/terms-tools"
            }
        }
    ]
}